{
  "alternateIdentifiers": [
    {
      "alternateIdentifier": "https://osf.io/9zesh",
      "alternateIdentifierType": "URL"
    }
  ],
  "contributors": [
    {
      "contributorName": {
        "contributorName": "Center for Open Science",
        "nameType": "Organizational"
      },
      "contributorType": "HostingInstitution",
      "nameIdentifier": {
        "nameIdentifier": "https://ror.org/05d5mza29",
        "nameIdentifierScheme": "ROR"
      }
    }
  ],
  "creators": [
    {
      "creatorName": {
        "creatorName": "Edward A. Vessel",
        "nameType": "Personal"
      },
      "nameIdentifier": {
        "nameIdentifier": "https://osf.io/k9huf",
        "nameIdentifierScheme": "URL"
      }
    }
  ],
  "dates": [
    {
      "date": "2023-06-17",
      "dateType": "Created"
    },
    {
      "date": "2023-06-17",
      "dateType": "Updated"
    }
  ],
  "descriptions": [],
  "fundingReferences": [],
  "identifier": {
    "identifier": "https://osf.io/9zesh",
    "identifierType": "URL"
  },
  "publicationYear": "2023",
  "publisher": "OSF",
  "relatedIdentifiers": [
    {
      "relatedIdentifier": "https://osf.io/6zxc5",
      "relatedIdentifierType": "URL",
      "relationType": "IsPartOf"
    }
  ],
  "relatedItems": [
    {
      "publicationYear": "2022",
      "publisher": "OSF",
      "relatedItemIdentifier": {
        "relatedItemIdentifier": "https://osf.io/6zxc5",
        "relatedItemIdentifierType": "URL"
      },
      "relatedItemType": "Text",
      "relationType": "IsPartOf",
      "titles": [
        {
          "title": "Self Relevance predicts Aesthetic Appeal"
        }
      ]
    }
  ],
  "resourceType": {
    "resourceType": "File",
    "resourceTypeGeneral": "Text"
  },
  "rightsList": [],
  "subjects": [],
  "titles": [
    {
      "title": "Exp1A_Data.txt"
    }
  ]
}